salesforce_reporting_chunked/__init__.py
salesforce_reporting_chunked/chunky.py
salesforce_reporting_chunked/report_chunker.py
salesforce_reporting_chunked-0.1.6.dist-info/LICENSE.txt
salesforce_reporting_chunked-0.1.6.dist-info/METADATA
salesforce_reporting_chunked-0.1.6.dist-info/WHEEL
salesforce_reporting_chunked-0.1.6.dist-info/top_level.txt
salesforce_reporting_chunked-0.1.6.dist-info/zip-safe
salesforce_reporting_chunked-0.1.6.dist-info/RECORD
