Metadata-Version: 2.1
Name: salesforce-reporting-chunked
Version: 0.1.6
Summary: Get > 2000 records from Salesforce reports with python.
Home-page: https://gitlab.com/doug.shawhan/salesforce-reporting-chunks
Author: Doug Shawhan
Author-email: doug.shawhan@gmail.com
License: MIT License
Keywords: python,salesforce,salesforce.com
Platform: UNKNOWN
Classifier: Programming Language :: Python :: 3
Requires-Dist: requests
Requires-Dist: salesforce-reporting
